iolanta_roadmap/__init__.py
iolanta_roadmap/cli.py
iolanta_roadmap/data/context.yaml
iolanta_roadmap/data/roadmap.yaml
iolanta_roadmap/facets/__init__.py
iolanta_roadmap/facets/base.py
iolanta_roadmap/facets/cli.py
iolanta_roadmap/facets/models.py
iolanta_roadmap/facets/sparql/tasks.sparql
iolanta_roadmap/facets/svg.py
iolanta_roadmap/plugin.py
iolanta_roadmap-0.1.0.dist-info/METADATA
iolanta_roadmap-0.1.0.dist-info/WHEEL
iolanta_roadmap-0.1.0.dist-info/entry_points.txt
iolanta_roadmap-0.1.0.dist-info/RECORD
